django_react_components/__init__.py
django_react_components/apps.py
django_react_components/checks.py
django_react_components/templatetags/__init__.py
django_react_components/templatetags/django_react_components.py
django_react_components-1.1.0.dist-info/licenses/LICENSE
django_react_components-1.1.0.dist-info/METADATA
django_react_components-1.1.0.dist-info/WHEEL
django_react_components-1.1.0.dist-info/top_level.txt
django_react_components-1.1.0.dist-info/RECORD
